testzeus_cli/__init__.py
testzeus_cli/auth.py
testzeus_cli/cli.py
testzeus_cli/commands/__init__.py
testzeus_cli/commands/environments.py
testzeus_cli/commands/extensions.py
testzeus_cli/commands/notification_channels.py
testzeus_cli/commands/tags.py
testzeus_cli/commands/test_data.py
testzeus_cli/commands/test_report_schedules.py
testzeus_cli/commands/test_run_groups.py
testzeus_cli/commands/test_runs.py
testzeus_cli/commands/tests.py
testzeus_cli/commands/tests_ai_generator.py
testzeus_cli/config.py
testzeus_cli/utils/__init__.py
testzeus_cli/utils/auth.py
testzeus_cli/utils/client.py
testzeus_cli/utils/formatters.py
testzeus_cli/utils/validators.py
testzeus_cli-0.0.16.dist-info/METADATA
testzeus_cli-0.0.16.dist-info/WHEEL
testzeus_cli-0.0.16.dist-info/entry_points.txt
testzeus_cli-0.0.16.dist-info/licenses/LICENSE
testzeus_cli-0.0.16.dist-info/RECORD
