Metadata-Version: 2.4
Name: testzeus-cli
Version: 0.0.16
Summary: Command-line interface for TestZeus testing platform
License-File: LICENSE
Author: Shriyansh Agnihotri
Author-email: shriyansh@testzeus.com
Requires-Python: >=3.11,<3.14
Classifier: License :: OSI Approved :: MIT License
Classifier: Programming Language :: Python :: 3
Classifier: Programming Language :: Python :: 3.11
Classifier: Programming Language :: Python :: 3.12
Classifier: Programming Language :: Python :: 3.13
Requires-Dist: click (>=8.1.3,<9.0.0)
Requires-Dist: ipdb (>=0.13.13,<0.14.0)
Requires-Dist: keyring (>=24.0.0,<25.0.0)
Requires-Dist: pocketbase (>=0.15.0,<0.16.0)
Requires-Dist: pydantic (>=2.0.0,<3.0.0)
Requires-Dist: pyyaml (>=6.0,<7.0)
Requires-Dist: rich (>=13.3.1,<14.0.0)
Requires-Dist: testzeus-sdk (>=0.0.15,<0.0.16)
Requires-Dist: toml (>=0.10.2,<0.11.0)
Project-URL: Repository, https://github.com/test-zeus-ai/testzeus-cli
